[
    {
        "name":"employee_directory",
        "path":"employee_directory.jpg",
        "gif":"employee_directory.gif"
    },
    {
        "name":"budget_tracker",
        "path":"budget_tracker.jpg",
        "gif":"budget_tracker.gif"
    },
    {
        "name":"exerciseMe",
        "path":"exerciseMe.jpg",
        "gif":"exerciseMe.gif"
    },
    {
        "name":"burger",
        "path":"burger.jpg",
        "gif":"burger.gif"
    },
    {
        "name":"weather",
        "path":"weather.jpg",
        "gif":"weather.gif"
    },
    {
        "name":"notes",
        "path":"notes.jpg",
        "gif":"notes.gif"
    },
    {
        "name":"scheduler",
        "path":"scheduler.jpg",
        "gif":"scheduler.gif"
    },
    {
        "name":"password",
        "path":"password.jpg",
        "gif":"password.gif"
    },
    {
        "name":"readMe",
        "path":"readMe.jpg",
        "gif":"readMe.gif"
    }
]